parse_iex/__init__.py
parse_iex/tops.py
parse_iex-0.1.1.dist-info/LICENSE
parse_iex-0.1.1.dist-info/WHEEL
parse_iex-0.1.1.dist-info/METADATA
parse_iex-0.1.1.dist-info/RECORD
