Metadata-Version: 2.1
Name: parse-iex
Version: 0.1.1
Summary: Parse IEX market data streams
Home-page: https://github.com/mmatamm/parse-IEX
License: BSD-2-Clause
Keywords: IEX
Author: Amit Goren
Requires-Python: >=3.10,<4.0
Classifier: License :: OSI Approved :: BSD License
Classifier: Programming Language :: Python :: 3
Classifier: Programming Language :: Python :: 3.10
Project-URL: Repository, https://github.com/mmatamm/parse-IEX.git
